anacreonlib/__init__.py
anacreonlib/anacreon.py
anacreonlib/anacreon_async_client.py
anacreonlib/anacreon_async_client.pyi
anacreonlib/exceptions.py
anacreonlib/py.typed
anacreonlib/utils.py
anacreonlib/types/__init__.py
anacreonlib/types/_deser_utils.py
anacreonlib/types/request_datatypes.py
anacreonlib/types/response_datatypes.py
anacreonlib/types/scenario_info_datatypes.py
anacreonlib/types/type_hints.py
anacreonlib-2.0.1.dist-info/LICENSE
anacreonlib-2.0.1.dist-info/METADATA
anacreonlib-2.0.1.dist-info/WHEEL
anacreonlib-2.0.1.dist-info/top_level.txt
anacreonlib-2.0.1.dist-info/RECORD
