Metadata-Version: 2.1
Name: anacreonlib
Version: 2.0.1
Summary: This library provides a Python interface to the API of Anacreon 3, which is an online 4X game
Home-page: https://github.com/ritikmishra/anacreonlib
Author: Ritik Mishra
Author-email: ritik.mishra314@gmail.com
License: MIT
Platform: UNKNOWN
Classifier: Development Status :: 3 - Alpha
Classifier: License :: OSI Approved :: MIT License
Classifier: Operating System :: OS Independent
Classifier: Programming Language :: Python :: 3.8
Requires-Python: >=3.8
Requires-Dist: pydantic
Requires-Dist: uplink[aiohttp]
